Metadata-Version: 2.4
Name: django-firebase-auth
Version: 1.2.4
Summary: Django authentication middle ware using Firebase Authentication Service
Home-page: https://github.com/maycuatroi/django-firebase-auth
Author: Nguyen Anh Binh
Author-email: sometimesocrazy@gmail.com
License: MIT License
License-File: LICENSE
Requires-Dist: firebase-admin
Requires-Dist: djangorestframework
Dynamic: author
Dynamic: author-email
Dynamic: description
Dynamic: description-content-type
Dynamic: home-page
Dynamic: license
Dynamic: license-file
Dynamic: requires-dist
Dynamic: summary
